torch_hd-5.8.4.dist-info/licenses/LICENSE
torchhd/__init__.py
torchhd/classifiers.py
torchhd/embeddings.py
torchhd/functional.py
torchhd/memory.py
torchhd/models.py
torchhd/structures.py
torchhd/types.py
torchhd/utils.py
torchhd/version.py
torchhd/datasets/__init__.py
torchhd/datasets/abalone.py
torchhd/datasets/acute_inflammation.py
torchhd/datasets/acute_nephritis.py
torchhd/datasets/adult.py
torchhd/datasets/airfoil_self_noise.py
torchhd/datasets/annealing.py
torchhd/datasets/arrhythmia.py
torchhd/datasets/audiology_std.py
torchhd/datasets/balance_scale.py
torchhd/datasets/balloons.py
torchhd/datasets/bank.py
torchhd/datasets/beijing_air_quality.py
torchhd/datasets/blood.py
torchhd/datasets/breast_cancer.py
torchhd/datasets/breast_cancer_wisc.py
torchhd/datasets/breast_cancer_wisc_diag.py
torchhd/datasets/breast_cancer_wisc_prog.py
torchhd/datasets/breast_tissue.py
torchhd/datasets/car.py
torchhd/datasets/cardiotocography_10clases.py
torchhd/datasets/cardiotocography_3clases.py
torchhd/datasets/ccpp.py
torchhd/datasets/chess_krvk.py
torchhd/datasets/chess_krvkp.py
torchhd/datasets/congressional_voting.py
torchhd/datasets/conn_bench_sonar_mines_rocks.py
torchhd/datasets/conn_bench_vowel_deterding.py
torchhd/datasets/connect_4.py
torchhd/datasets/contrac.py
torchhd/datasets/credit_approval.py
torchhd/datasets/cylinder_bands.py
torchhd/datasets/dataset.py
torchhd/datasets/dermatology.py
torchhd/datasets/echocardiogram.py
torchhd/datasets/ecoli.py
torchhd/datasets/emg_hand_gestures.py
torchhd/datasets/energy_y1.py
torchhd/datasets/energy_y2.py
torchhd/datasets/european_languages.py
torchhd/datasets/fertility.py
torchhd/datasets/flags.py
torchhd/datasets/glass.py
torchhd/datasets/haberman_survival.py
torchhd/datasets/hayes_roth.py
torchhd/datasets/heart_cleveland.py
torchhd/datasets/heart_hungarian.py
torchhd/datasets/heart_switzerland.py
torchhd/datasets/heart_va.py
torchhd/datasets/hepatitis.py
torchhd/datasets/hill_valley.py
torchhd/datasets/horse_colic.py
torchhd/datasets/ilpd_indian_liver.py
torch_hd-5.8.4.dist-info/METADATA
torch_hd-5.8.4.dist-info/WHEEL
torch_hd-5.8.4.dist-info/top_level.txt
torch_hd-5.8.4.dist-info/RECORD
