Metadata-Version: 2.4
Name: torch-hd
Version: 5.8.4
Summary: Torchhd is a Python library for Hyperdimensional Computing and Vector Symbolic Architectures
Home-page: https://github.com/hyperdimensional-computing/torchhd
License: MIT
Project-URL: Source, https://github.com/hyperdimensional-computing/torchhd
Project-URL: Documentation, https://torchhd.readthedocs.io
Requires-Python: >=3.8, <4
License-File: LICENSE
Requires-Dist: torch>=1.9.0
Requires-Dist: scipy
Requires-Dist: pandas
Requires-Dist: numpy
Requires-Dist: requests
Requires-Dist: tqdm
Requires-Dist: openpyxl
Dynamic: description
Dynamic: description-content-type
Dynamic: home-page
Dynamic: license
Dynamic: license-file
Dynamic: project-url
Dynamic: requires-dist
Dynamic: requires-python
Dynamic: summary
